.gitignore
LICENSE.txt
MANIFEST.in
Makefile
README.md
environment.yml
pyproject.toml
setup.py
.binder/requirements.txt
.build_tools/travis/install.sh
.build_tools/travis/test_script.sh
.github/workflows/build-html-and-deploy.yml
.github/workflows/test.yml
circhic/__init__.py
circhic/_base.py
circhic/setup.py
circhic/utils.py
circhic.egg-info/PKG-INFO
circhic.egg-info/SOURCES.txt
circhic.egg-info/dependency_links.txt
circhic.egg-info/top_level.txt
circhic/datasets/__init__.py
circhic/datasets/_base.py
circhic/datasets/setup.py
circhic/datasets/data/KBM7/HIC_076_50000_chr11.bed
circhic/datasets/data/KBM7/HIC_076_50000_chr11.matrix
circhic/datasets/data/KBM7/HIC_076_50000_chr14.bed
circhic/datasets/data/KBM7/HIC_076_50000_chr14.matrix
circhic/datasets/data/bsubtilis/SRX1014144_9790.matrix
circhic/datasets/data/bsubtilis/SRX1014144_9790_abs.bed
circhic/datasets/data/bsubtilis/SRX1014144_9790_iced.matrix
circhic/datasets/data/bsubtilis/SRX1014144_9790_iced.matrix.biases
circhic/datasets/data/ccrescentus/SRX263925_9958.matrix
circhic/datasets/data/ccrescentus/SRX263925_9958_abs.bed
circhic/datasets/data/ccrescentus/SRX263925_9958_iced.matrix
circhic/datasets/data/ccrescentus/SRX263925_9958_iced.matrix.biases
circhic/datasets/data/ecoli/SRX3451210_9897.matrix
circhic/datasets/data/ecoli/SRX3451210_9897_abs.bed
circhic/datasets/data/ecoli/SRX3451210_9897_iced.matrix
circhic/datasets/data/ecoli/SRX3451210_9897_iced.matrix.biases
circhic/datasets/tests/test_base.py
circhic/tests/test__base.py
circhic/tests/test_utils.py
doc/.gitignore
doc/Makefile
doc/conf.py
doc/index.rst
doc/install.rst
doc/make.bat
doc/principle.rst
doc/releasing.rst
doc/user_guide.rst
doc/_static/css/bootstrap.css
doc/_static/css/bootstrap.min.css
doc/_static/css/jhepc.css
doc/_static/js/bootstrap.js
doc/_static/js/bootstrap.min.js
doc/_static/js/jquery.js
doc/_static/js/jquery.maphilight.js
doc/_static/js/jquery.maphilight.min.js
doc/_static/logos/button_blue.png
doc/_static/logos/button_blue.svg
doc/_static/logos/button_green.png
doc/_static/logos/button_green.svg
doc/_static/logos/button_orange.png
